stbs/__init__.py
stbs-0.0.1.dist-info/LICENSE
stbs-0.0.1.dist-info/METADATA
stbs-0.0.1.dist-info/WHEEL
stbs-0.0.1.dist-info/top_level.txt
stbs-0.0.1.dist-info/RECORD
