Metadata-Version: 2.1
Name: stbs
Version: 0.0.1
Summary: A small and easy to use package to create Timers.
Home-page: https://github.com/Shaunters/SimpleTimer_Module
Author: Shaunters
Author-email: brshaunters@gmail.com
License: UNKNOWN
Platform: UNKNOWN
Classifier: Programming Language :: Python :: 3
Classifier: License :: OSI Approved :: MIT License
Classifier: Operating System :: OS Independent
Requires-Python: >=3.6
